ml_example/__init__.py
ml_example/train_pipeline.py
ml_example/data/__init__.py
ml_example/data/make_dataset.py
ml_example/enities/__init__.py
ml_example/enities/feature_params.py
ml_example/enities/split_params.py
ml_example/enities/train_params.py
ml_example/enities/train_pipeline_params.py
ml_example/features/__init__.py
ml_example/features/build_features.py
ml_example/models/__init__.py
ml_example/models/model_fit_predict.py
tests/__init__.py
tests/conftest.py
tests/test_end2end_training.py
tests/data/__init__.py
tests/data/test_make_dataset.py
tests/features/__init__.py
tests/features/test_make_categorical_features.py
tests/features/test_make_features.py
tests/models/__init__.py
tests/models/test_train_model.py
ml_example-0.1.0.dist-info/LICENSE
ml_example-0.1.0.dist-info/METADATA
ml_example-0.1.0.dist-info/WHEEL
ml_example-0.1.0.dist-info/top_level.txt
ml_example-0.1.0.dist-info/RECORD
