Metadata-Version: 2.1
Name: ml-example
Version: 0.1.0
Summary: Example of ml project
Home-page: UNKNOWN
Author: Your name (or your organization/company/team)
Author-email: UNKNOWN
License: MIT
Platform: UNKNOWN
